{
 "meta": {
  "ticker": "VTBR",
  "name": "Банк ВТБ (ПАО)",
  "as_of": "2026-07-03",
  "data_quality": "medium",
  "macro_regime_summary": "Ставка снижается с пика 21% (спот 14,25%), но FY2025 прошёл при средней ~18% — NIM был на троге 0,52%. Для ВТБ с тонкой маржой разворот ставки — главный рычаг восстановления прибыли; сдерживают рост стоимости риска, зарплатная инфляция и тонкий капитал.",
  "overall_effect": "mixed",
  "main_risk": "маржа",
  "certainty_legend": {
   "fact": "Факт с источником — текущий макропоказатель",
   "logic": "Логика — канал влияния (надёжная экономическая теория)",
   "judgement": "Суждение — сила/срок эффекта, прогноз, относительный взгляд; «на наш взгляд»"
  }
 },
 "current_financials": {
  "period": "FY2025 (МСФО, группа)",
  "revenue": {
   "value": "985,4 млрд ₽ (операц. доход до резервов и расходов)",
   "certainty": "fact",
   "source_ref": "src_f1"
  },
  "ebitda": {
   "value": "425,1 млрд ₽ (доресервная операционная прибыль ≈ банковский аналог)",
   "certainty": "fact",
   "source_ref": "src_f1"
  },
  "net_profit": {
   "value": "483,7 млрд ₽ отчётная / ≈363,7 млрд нормализованная",
   "certainty": "fact",
   "source_ref": "src_f1"
  },
  "fx_revenue_share": "~2% (домашний банк, международный бизнес свёрнут после 2022 — курс почти не влияет операционно)",
  "debt": {
   "total": "фондирование: депозиты клиентов 30 021 млрд ₽ + межбанк/выпущенные ц/б/субдолг; для банка «долг» ≈ платные пассивы",
   "floating_share": "высокая доля переоцениваемых пассивов (срочные депозиты) и активов (корпкредиты часто по плавающей) → банк liability-sensitive",
   "avg_cost": "стоимость фондирования выросла вслед за ставкой; ЧПД FY2025 сжат до 190,4 млрд (NIM 0,52% в среднем за год при средней ставке ~18%)",
   "fx_share": "минимальная (валютные операции заблокированы санкциями)",
   "near_term_refi": "депозитная база переоценивается вниз при снижении ставки с лагом 3-6 мес — источник восстановления NIM в 2026",
   "certainty": "fact",
   "source_ref": "src_f1"
  }
 },
 "quant_inputs": {
  "unit": "млрд_руб",
  "financials": {
   "revenue": 985.4,
   "ebitda": 425.1,
   "net_profit": 483.7,
   "fiscal_year": "2025"
  },
  "macro_current": {
   "fx_usdrub": 78.7,
   "key_rate_pct": 18.0,
   "commodity_usd": null,
   "gdp_growth_pct": 1.5,
   "wage_growth_pp": 13.0,
   "cor_bps": 99
  },
  "macro_neutral": {
   "fx_usdrub": 88,
   "key_rate_pct": 11,
   "commodity_usd": null,
   "gdp_growth_pct": 1.7,
   "wage_growth_pp": 8.0,
   "cor_bps": 115
  },
  "coefficients": {
   "rate": {
    "per": "100bp",
    "revenue": -35,
    "ebitda": -32,
    "net_profit": -25,
    "source": "estimated",
    "assumption": "NIM-канал (НЕ проценты по долгу): ВТБ liability-sensitive — при росте ставки дорогое срочное/корпоративное фондирование дорожает быстрее доходности активов, NIM сжимается; при снижении пассивы переоцениваются вниз, NIM расширяется. Коэффициент −25 млрд ЧП/−100 б.п. — БЛЕНДОВАЯ (эффективная) величина, откалибрована так, чтобы путь ставки со средней-2025 (~18%) к средней-2026 совпал с гайденсом менеджмента (норм. ~500 / отчётн. 600-650). У трога NIM отскакивает круче (~0,3-0,4 пп/100 б.п.), у нейтрали площе — линейный коэффициент усредняет ~0,10-0,15 пп/100 б.п. на ~30 трлн работающих активов"
   },
   "demand": {
    "per": "1pp_gdp",
    "revenue": 12,
    "ebitda": 8,
    "net_profit": 7,
    "source": "estimated",
    "assumption": "ВВП → рост кредитного портфеля → объём ЧПД; для 2026 менеджмент ждёт корпорат +10%, розница −5% — эффект умеренно положительный, но вторичен к NIM"
   },
   "labor": {
    "per": "1pp_wage",
    "revenue": null,
    "ebitda": -2.5,
    "net_profit": -1.9,
    "source": "estimated",
    "assumption": "дефицит труда → рост зарплат → ФОТ (≈45% opex 560,3 млрд ≈253 млрд) ↑ → CIR ↑ → доресервная прибыль ↓. +1пп роста зарплат ≈ +2,53 млрд расходов до налога ≈ −1,9 млрд ЧП (×0,75); ±5пп opex ≈ ±28 млрд до налога. Дезинфляция зарплат — недооценённая часть голубиного апсайда"
   },
   "cost_of_risk": {
    "driver": "cor_bps",
    "label": "Стоимость риска (резервы)",
    "per": "1bp",
    "net_profit": -1.84,
    "source": "estimated",
    "assumption": "качество активов ВТБ слабее сектора; through-cycle CoR ~1,15-1,2% принят нейтралью. +1бп CoR на портфеле ~24,6 трлн ≈ +2,46 млрд резервов до налога ≈ −1,84 млрд ЧП. FY2025 факт 0,99% — НИЖЕ нормы (умеренные резервы); forward-риск — рост розничной просрочки к 6-7% толкает CoR к 1,1-1,35%"
   }
  },
  "one_off": {
   "label": "Признание отложенного налогового актива и роспуск части резервов (2025)",
   "net_profit": 120,
   "certainty": "estimate",
   "note": "разовое; операционная ЧП 2025 ≈ 363,7 млрд против отчётных 483,7 млрд"
  },
  "neutral_net_profit": 490,
  "scenarios": {
   "base": {
    "fx_usdrub": 83,
    "key_rate_pct": 12,
    "commodity_usd": null,
    "gdp_growth_pct": 1.8,
    "wage_growth_pp": 11.0,
    "cor_bps": 105,
    "probability": "вероятнее"
   },
   "hawkish": {
    "fx_usdrub": 90,
    "key_rate_pct": 15,
    "commodity_usd": null,
    "gdp_growth_pct": 0.8,
    "wage_growth_pp": 14.0,
    "cor_bps": 135,
    "probability": "риск"
   },
   "dovish": {
    "fx_usdrub": 80,
    "key_rate_pct": 10,
    "commodity_usd": null,
    "gdp_growth_pct": 2.5,
    "wage_growth_pp": 9.0,
    "cor_bps": 95,
    "probability": "менее вероятно"
   }
  },
  "macro_spot": {
   "fx_usdrub": 78.7,
   "key_rate_pct": 14.25,
   "commodity_usd": null,
   "gdp_growth_pct": 1.5,
   "wage_growth_pp": 13.0,
   "cor_bps": 99
  },
  "_macro_spot_note": "macro_current=средние условия FY2025 (якорь атрибуции); macro_spot=сегодня (спот ставки 14.25) для forward-сценариев"
 },
 "computed": {
  "attribution": {
   "neutral_net_profit": 490,
   "bridge": [
    {
     "factor_key": "rate",
     "label": "Ставка (процентный канал)",
     "delta": -175,
     "is_one_off": false,
     "source": "estimated",
     "assumption": "NIM-канал (НЕ проценты по долгу): ВТБ liability-sensitive — при росте ставки дорогое срочное/корпоративное фондирование дорожает быстрее доходности активов, NIM сжимается; при снижении пассивы переоцениваются вниз, NIM расширяется. Коэффициент −25 млрд ЧП/−100 б.п. — БЛЕНДОВАЯ (эффективная) величина, откалибрована так, чтобы путь ставки со средней-2025 (~18%) к средней-2026 совпал с гайденсом менеджмента (норм. ~500 / отчётн. 600-650). У трога NIM отскакивает круче (~0,3-0,4 пп/100 б.п.), у нейтрали площе — линейный коэффициент усредняет ~0,10-0,15 пп/100 б.п. на ~30 трлн работающих активов",
     "calc": {
      "coef": -25,
      "per": "100bp",
      "from": 11.0,
      "to": 18.0,
      "shift": 7.0
     }
    },
    {
     "factor_key": "demand",
     "label": "Спрос / ВВП (канал ставки)",
     "delta": -1.4,
     "is_one_off": false,
     "source": "estimated",
     "assumption": "ВВП → рост кредитного портфеля → объём ЧПД; для 2026 менеджмент ждёт корпорат +10%, розница −5% — эффект умеренно положительный, но вторичен к NIM",
     "calc": {
      "coef": 7.0,
      "per": "1pp_gdp",
      "from": 1.7,
      "to": 1.5,
      "shift": -0.2
     }
    },
    {
     "factor_key": "labor",
     "label": "Рынок труда / зарплаты",
     "delta": -9.5,
     "is_one_off": false,
     "source": "estimated",
     "assumption": "дефицит труда → рост зарплат → ФОТ (≈45% opex 560,3 млрд ≈253 млрд) ↑ → CIR ↑ → доресервная прибыль ↓. +1пп роста зарплат ≈ +2,53 млрд расходов до налога ≈ −1,9 млрд ЧП (×0,75); ±5пп opex ≈ ±28 млрд до налога. Дезинфляция зарплат — недооценённая часть голубиного апсайда",
     "calc": {
      "coef": -1.9,
      "per": "1pp_wage",
      "from": 8.0,
      "to": 13.0,
      "shift": 5.0
     }
    },
    {
     "factor_key": "cost_of_risk",
     "label": "Стоимость риска (резервы)",
     "delta": 29,
     "is_one_off": false,
     "source": "estimated",
     "assumption": "качество активов ВТБ слабее сектора; through-cycle CoR ~1,15-1,2% принят нейтралью. +1бп CoR на портфеле ~24,6 трлн ≈ +2,46 млрд резервов до налога ≈ −1,84 млрд ЧП. FY2025 факт 0,99% — НИЖЕ нормы (умеренные резервы); forward-риск — рост розничной просрочки к 6-7% толкает CoR к 1,1-1,35%",
     "calc": {
      "coef": -1.8,
      "per": "1bp",
      "from": 115.0,
      "to": 99.0,
      "shift": -16
     }
    }
   ],
   "residual": 30,
   "operating_net_profit": 364,
   "actual_net_profit": 484,
   "one_off": {
    "label": "Признание отложенного налогового актива и роспуск части резервов (2025)",
    "net_profit": 120,
    "note": "разовое; операционная ЧП 2025 ≈ 363,7 млрд против отчётных 483,7 млрд",
    "certainty": "estimate"
   },
   "main_driver": "rate",
   "unit": "млрд_руб"
  },
  "sensitivities": [
   {
    "factor_key": "rate",
    "label": "Ставка (процентный канал)",
    "per": "100bp",
    "revenue": -35,
    "ebitda": -32,
    "net_profit": -25,
    "source": "estimated",
    "assumption": "NIM-канал (НЕ проценты по долгу): ВТБ liability-sensitive — при росте ставки дорогое срочное/корпоративное фондирование дорожает быстрее доходности активов, NIM сжимается; при снижении пассивы переоцениваются вниз, NIM расширяется. Коэффициент −25 млрд ЧП/−100 б.п. — БЛЕНДОВАЯ (эффективная) величина, откалибрована так, чтобы путь ставки со средней-2025 (~18%) к средней-2026 совпал с гайденсом менеджмента (норм. ~500 / отчётн. 600-650). У трога NIM отскакивает круче (~0,3-0,4 пп/100 б.п.), у нейтрали площе — линейный коэффициент усредняет ~0,10-0,15 пп/100 б.п. на ~30 трлн работающих активов"
   },
   {
    "factor_key": "demand",
    "label": "Спрос / ВВП (канал ставки)",
    "per": "1pp_gdp",
    "revenue": 12,
    "ebitda": 8.0,
    "net_profit": 7.0,
    "source": "estimated",
    "assumption": "ВВП → рост кредитного портфеля → объём ЧПД; для 2026 менеджмент ждёт корпорат +10%, розница −5% — эффект умеренно положительный, но вторичен к NIM"
   },
   {
    "factor_key": "labor",
    "label": "Рынок труда / зарплаты",
    "per": "1pp_wage",
    "revenue": null,
    "ebitda": -2.5,
    "net_profit": -1.9,
    "source": "estimated",
    "assumption": "дефицит труда → рост зарплат → ФОТ (≈45% opex 560,3 млрд ≈253 млрд) ↑ → CIR ↑ → доресервная прибыль ↓. +1пп роста зарплат ≈ +2,53 млрд расходов до налога ≈ −1,9 млрд ЧП (×0,75); ±5пп opex ≈ ±28 млрд до налога. Дезинфляция зарплат — недооценённая часть голубиного апсайда"
   },
   {
    "factor_key": "cost_of_risk",
    "label": "Стоимость риска (резервы)",
    "per": "1bp",
    "revenue": null,
    "ebitda": null,
    "net_profit": -1.8,
    "source": "estimated",
    "assumption": "качество активов ВТБ слабее сектора; through-cycle CoR ~1,15-1,2% принят нейтралью. +1бп CoR на портфеле ~24,6 трлн ≈ +2,46 млрд резервов до налога ≈ −1,84 млрд ЧП. FY2025 факт 0,99% — НИЖЕ нормы (умеренные резервы); forward-риск — рост розничной просрочки к 6-7% толкает CoR к 1,1-1,35%"
   }
  ],
  "scenarios": {
   "base": {
    "probability": "вероятнее",
    "macro": {
     "fx_usdrub": 83,
     "key_rate_pct": 12
    },
    "revenue_delta": 82,
    "ebitda_delta": 79,
    "net_profit_delta": 51,
    "contributions": {
     "rate": {
      "revenue": 79,
      "ebitda": 72,
      "net_profit": 56
     },
     "demand": {
      "revenue": 3.6,
      "ebitda": 2.4,
      "net_profit": 2.1
     },
     "labor": {
      "ebitda": 5.0,
      "net_profit": 3.8
     },
     "cost_of_risk": {
      "net_profit": -11
     }
    }
   },
   "hawkish": {
    "probability": "риск",
    "macro": {
     "fx_usdrub": 90,
     "key_rate_pct": 15
    },
    "revenue_delta": -35,
    "ebitda_delta": -32,
    "net_profit_delta": -92,
    "contributions": {
     "rate": {
      "revenue": -26,
      "ebitda": -24,
      "net_profit": -19
     },
     "demand": {
      "revenue": -8.4,
      "ebitda": -5.6,
      "net_profit": -4.9
     },
     "labor": {
      "ebitda": -2.5,
      "net_profit": -1.9
     },
     "cost_of_risk": {
      "net_profit": -66
     }
    }
   },
   "dovish": {
    "probability": "менее вероятно",
    "macro": {
     "fx_usdrub": 80,
     "key_rate_pct": 10
    },
    "revenue_delta": 161,
    "ebitda_delta": 154,
    "net_profit_delta": 128,
    "contributions": {
     "rate": {
      "revenue": 149,
      "ebitda": 136,
      "net_profit": 106
     },
     "demand": {
      "revenue": 12,
      "ebitda": 8.0,
      "net_profit": 7.0
     },
     "labor": {
      "ebitda": 10,
      "net_profit": 7.6
     },
     "cost_of_risk": {
      "net_profit": 7.4
     }
    }
   }
  },
  "checks": {
   "waterfall_has_residual": true,
   "residual": 30,
   "residual_pct_of_neutral": 6.1,
   "factors_count": 4
  },
  "_note": "computed by backend/app/services/macro_quant.py"
 },
 "snapshot": [
  {
   "indicator": "Ключевая ставка ЦБ",
   "value": "14,25%",
   "trend": "down",
   "trend_note": "−25 б.п. 19.06.2026; снижается с пика 21%. Средняя за FY2025 ~18% — важно для сверки с прибылью 2025",
   "certainty": "fact",
   "source_ref": "src_1"
  },
  {
   "indicator": "Инфляция г/г",
   "value": "5,6%",
   "trend": "down",
   "trend_note": "устойчивая 4-5% в пересчёте на год; инфляц. ожидания остаются повышенными",
   "certainty": "fact",
   "source_ref": "src_1"
  },
  {
   "indicator": "NIM ВТБ",
   "value": "3,3% (1кв2026)",
   "trend": "up",
   "trend_note": "восстановление с 0,52% в среднем за 2025 по мере снижения ставки — ключевой драйвер прибыли",
   "certainty": "fact",
   "source_ref": "src_3"
  },
  {
   "indicator": "Стоимость риска (CoR) ВТБ",
   "value": "~1,0-1,1%",
   "trend": "up",
   "trend_note": "FY2025 0,99% (ниже through-cycle ~1,2%); прогноз 2026 ~1,1% (корп 0,8% / розница 2,1%), риск роста розничной просрочки к 6-7%",
   "certainty": "fact",
   "source_ref": "src_3"
  },
  {
   "indicator": "Достаточность капитала Н20.0",
   "value": "9,8%",
   "trend": "flat",
   "trend_note": "при минимуме с надбавками ≈10% на 2026; цель 2026 ≥10,5% — буфер почти исчерпан",
   "certainty": "fact",
   "source_ref": "src_f1"
  },
  {
   "indicator": "USD/RUB",
   "value": "~78-79",
   "trend": "up",
   "trend_note": "рубль ослаб в июне на снижении нефти; для домашнего банка эффект косвенный (через инфляцию/ставку)",
   "certainty": "fact",
   "source_ref": "src_2"
  }
 ],
 "factors": [
  {
   "factor": "Высокая, но снижающаяся ставка → NIM",
   "type": "rate",
   "current_state": {
    "text": "Средняя ставка FY2025 ~18% обвалила NIM до 0,52% (ЧПД лишь 190,4 млрд — меньше комиссий 307,1 млрд!). Спот 14,25% и снижение с пика 21% уже развернули маржу: в 1кв2026 NIM восстановился до 3,3%.",
    "certainty": "fact",
    "source_ref": "src_3"
   },
   "channel": "ставка ↑ → дорогое срочное/корпоративное фондирование ВТБ дорожает быстрее доходности активов (банк liability-sensitive) → NIM сжимается → ЧПД падает → прибыль вниз; ставка ↓ → пассивы переоцениваются вниз с лагом → NIM расширяется → прибыль восстанавливается",
   "channel_certainty": "logic",
   "second_layer": "У ВТБ мало дешёвых текущих счетов (в отличие от Сбера с его зарплатной базой) и портфель корпоративно-тяжёлый (70%) → маржа структурно тоньше, а чувствительность к ставке ВЫШЕ. ВТБ — «усилитель» цикла ставки: теряет больше на пике, но и отскакивает сильнее на развороте. NIM-сенса нелинейна: у трога круче, у нейтрали площе — нельзя копировать знак/силу Сбера.",
   "second_layer_certainty": "judgement",
   "effect_sign": "mixed",
   "effect_horizon": "уровень давил в 2025; вектор (снижение) — позитив на 2-4 квартала с лагом 3-6 мес",
   "effect_strength_certainty": "judgement",
   "quant_impact": {
    "metric": "net_profit",
    "estimate": "каждые −100 б.п. ставки ≈ +25 млрд ₽ к ЧП (блендовая эффективная величина, согласованная с гайденсом; у трога отскок круче ~0,3-0,4 пп NIM/100 б.п.); средняя ставка FY2025 ~18% против нейтральной 11% «съела» ~175 млрд операционной прибыли",
    "assumption": "работающие активы ~30 трлн ₽, эффективная NIM-сенса ~0,10-0,15 пп/100 б.п. по пути нормализации, лаг переоценки пассивов 3-6 мес, налог 25%",
    "is_one_off": false,
    "certainty": "estimate"
   },
   "note": "Главный фактор кейса. Для ВТБ траектория ставки важнее её уровня — банк максимально выигрывает от смягчения.",
   "source_refs": [
    "src_1",
    "src_3"
   ]
  },
  {
   "factor": "Стоимость риска и качество активов",
   "type": "demand",
   "current_state": {
    "text": "FY2025 CoR 0,99% (резервы ~243 млрд) — умеренный, НИЖЕ through-cycle медианы ВТБ ~1,15-1,2%; в 2024 был аномально низкий 0,3% (роспуск резервов). Прогноз 2026 ~1,1%, розничная просрочка к 6-7%.",
    "certainty": "fact",
    "source_ref": "src_3"
   },
   "channel": "высокая ставка дольше → нагрузка на заёмщиков (особенно розница, МСБ) растёт → дефолты и просрочка ↑ → резервы под кредитные убытки ↑ → прибыль вниз (ниже доресервной)",
   "channel_certainty": "logic",
   "second_layer": "У ВТБ качество активов исторически слабее сектора, а буфер капитала тонкий — рост резервов бьёт двойным ударом: и по прибыли, и по нормативу Н20.0. В 2025 CoR был ниже нормы (небольшой попутный ветер), но forward — главный риск: розничная просрочка вызревает медленно и толкает CoR к 1,1-1,35%.",
   "second_layer_certainty": "judgement",
   "effect_sign": "negative",
   "effect_horizon": "среднесрок 2026, розничная просрочка — с лагом",
   "effect_strength_certainty": "judgement",
   "quant_impact": {
    "metric": "net_profit",
    "estimate": "каждые +10 б.п. CoR ≈ −18 млрд ₽ к ЧП; FY2025 (99 б.п.) относительно through-cycle нейтрали 115 б.п. дал ~+29 млрд попутного ветра, но нормализация/рост к 105-135 б.п. — forward-риск на десятки млрд",
    "assumption": "кредитный портфель ~24,6 трлн ₽, налог 25%",
    "is_one_off": false,
    "certainty": "estimate"
   },
   "note": "Вторичный, но материальный канал; в отличие от Сбера у ВТБ меньше запаса прочности — риск форвардный.",
   "source_refs": [
    "src_3"
   ]
  },
  {
   "factor": "Зарплатная инфляция и издержки (ФОТ)",
   "type": "labor",
   "current_state": {
    "text": "Opex FY2025 вырос ~17% до 560,3 млрд, CIR подскочил до 57% (с 45% в 2024). ФОТ ≈45% расходов; дефицит кадров держит рост зарплат двузначным.",
    "certainty": "fact",
    "source_ref": "src_f1"
   },
   "channel": "дефицит труда → рост зарплат → ФОТ (≈45% opex) ↑ → операционные расходы ↑ → CIR ↑ → доресервная (операционная) прибыль ↓",
   "channel_certainty": "logic",
   "second_layer": "Для ВТБ с тонкой маржой рост CIR особенно болезнен: на сжатой NIM опережающий рост расходов съедает бОльшую долю операционного дохода, чем у Сбера. Зеркально — дезинфляция зарплат вместе с общей инфляцией является недооценённой частью голубиного апсайда (opex тормозит).",
   "second_layer_certainty": "judgement",
   "effect_sign": "negative",
   "effect_horizon": "структурный, весь 2026; ослабевает при дезинфляции",
   "effect_strength_certainty": "judgement",
   "quant_impact": {
    "metric": "net_profit",
    "estimate": "каждый +1 пп роста зарплат ≈ −1,9 млрд ₽ к ЧП; ±5 пп opex ≈ ±28 млрд до налога. Повышенный рост зарплат ~13% против нейтральных ~8% стоит ~−9-10 млрд",
    "assumption": "ФОТ ≈45% opex 560,3 млрд ≈253 млрд база; налог 25%",
    "is_one_off": false,
    "certainty": "estimate"
   },
   "note": "Недооценённый канал: на тонкой марже ВТБ рост CIR материален; дезинфляция зарплат — часть голубиного апсайда.",
   "source_refs": [
    "src_f1"
   ]
  },
  {
   "factor": "Тонкий капитал (Н20.0) и переоценка ОФЗ",
   "type": "rate",
   "current_state": {
    "text": "Н20.0 = 9,8% при минимуме с надбавками ≈10%; цель 2026 ≥10,5%. Портфель ценных бумаг ~5,4 трлн ₽ (в т.ч. ОФЗ). RGBI в июне 2026 упал к минимумам октября 2025.",
    "certainty": "fact",
    "source_ref": "src_f1"
   },
   "channel": "рост доходностей ОФЗ (при жёсткой ДКП/бюджетном давлении) → отрицательная переоценка облигационного портфеля → давление на капитал через OCI → ещё меньше буфера Н20.0 → ограничение роста RWA и дивидендов, риск новой допэмиссии (размывание)",
   "channel_certainty": "logic",
   "second_layer": "Это неочевидный для «обычного банка» канал: у ВТБ капитал — жёсткий ограничитель, поэтому макро бьёт не только по прибыли, но и по СПОСОБНОСТИ распределять её акционеру. При Н20.0 ≈9,8% значительная часть прибыли уходит на восстановление капитала (payout FY2025 ~25% вместо целевых 50%), а не акционерам.",
   "second_layer_certainty": "judgement",
   "effect_sign": "negative",
   "effect_horizon": "структурный, весь 2026",
   "effect_strength_certainty": "judgement",
   "quant_impact": {
    "metric": "net_profit",
    "estimate": "переоценка ОФЗ по FVTPL при росте доходностей — ориентировочно −10…20 млрд ₽ в квартал стресса (разово, волатильно); главный эффект — не P&L, а ограничение дивидендов и риск размывания",
    "assumption": "часть портфеля ~5,4 трлн в FVTPL, дюрация умеренная; FVOCI-часть бьёт по капиталу, минуя P&L",
    "is_one_off": true,
    "certainty": "judgement"
   },
   "note": "Уникальный ограничитель ВТБ — не столько прибыль, сколько капитал и дивиденды.",
   "source_refs": [
    "src_f1",
    "src_2"
   ]
  }
 ],
 "attribution": {
  "baseline_text": "При нейтральной ставке ~11% (вместо средней FY2025 ~18%), through-cycle стоимости риска ~115 б.п. и нейтральном росте зарплат ~8% операционная прибыль ВТБ была бы ориентировочно ~490 млрд ₽",
  "baseline_certainty": "judgement",
  "bridge": [
   {
    "factor": "Высокая ставка FY2025 ~18% (сжатие NIM)",
    "delta": "−≈175 млрд",
    "is_one_off": false,
    "certainty": "estimate"
   },
   {
    "factor": "Стоимость риска ниже нормы (попутный ветер 2025)",
    "delta": "+≈29 млрд",
    "is_one_off": false,
    "certainty": "estimate"
   },
   {
    "factor": "Зарплатная инфляция (рост ФОТ выше нейтрали)",
    "delta": "−≈10 млрд",
    "is_one_off": false,
    "certainty": "estimate"
   },
   {
    "factor": "Разовое: признание ОНА и роспуск резервов (2025)",
    "delta": "+120 млрд",
    "is_one_off": true,
    "certainty": "estimate"
   }
  ],
  "residual": "Неразложимый остаток ~+30 млрд (6% нейтрали) не подгоняется под факт: отражает нелинейность восстановления NIM — линейный коэффициент не ловит крутизну отскока маржи у трога. Ключ к атрибуции — измерение ставки от СРЕДНЕЙ FY2025 (~18%), а не от спота 14,25%, чтобы период макро совпал с якорной прибылью 2025.",
  "actual_net_profit": "483,7 млрд отчётная / ≈363,7 млрд нормализованная (факт)",
  "main_driver": "Сжатие NIM под высокой средней ставкой FY2025 ~18% — доминирующий канал: ЧПД 2025 обвалился до 190,4 млрд (меньше комиссий), именно ставка объясняет большую часть разрыва до нейтрали."
 },
 "sensitivities": [
  {
   "factor": "Ключевая ставка (через NIM)",
   "per_unit": "−100 б.п.",
   "revenue_delta": "+≈35 млрд (ЧПД)",
   "ebitda_delta": "+≈32 млрд",
   "net_profit_delta": "+≈25 млрд",
   "assumption": "блендовая эффективная NIM-сенса ~0,10-0,15 пп/100 б.п. по пути нормализации (у трога круче), работающие активы ~30 трлн, лаг 3-6 мес, налог 25%; ВТБ liability-sensitive (сильнее Сбера)",
   "source": "estimated",
   "certainty": "estimate"
  },
  {
   "factor": "Стоимость риска (CoR)",
   "per_unit": "+10 б.п.",
   "net_profit_delta": "−≈18 млрд",
   "assumption": "кредитный портфель ~24,6 трлн ₽, налог 25%",
   "source": "estimated",
   "certainty": "estimate"
  },
  {
   "factor": "Рост зарплат (ФОТ)",
   "per_unit": "+1 пп",
   "ebitda_delta": "−≈2,5 млрд",
   "net_profit_delta": "−≈1,9 млрд",
   "assumption": "ФОТ ≈45% opex 560,3 млрд ≈253 млрд, налог 25%",
   "source": "estimated",
   "certainty": "estimate"
  },
  {
   "factor": "Рост ВВП (объём кредита)",
   "per_unit": "+1 пп",
   "net_profit_delta": "+≈7 млрд",
   "assumption": "эластичность портфеля к ВВП ~1,5-2x, вторичен к марже",
   "source": "estimated",
   "certainty": "estimate"
  }
 ],
 "competitive_view": {
  "text": "Режим снижающейся ставки переупорядочивает банковский сектор в пользу тех, кто был максимально зажат высокой ставкой. ВТБ — «усилитель» цикла: на пике ставки его тонкая маржа страдала сильнее всех крупных банков, но на развороте NIM отскакивает мощнее. Ограничитель — тонкий капитал: в отличие от хорошо капитализированного Сбера, ВТБ не может свободно нарастить кредитование в фазе восстановления, а прибыль частично уходит на восстановление буфера, а не акционерам.",
  "who_benefits": [
   "банки с высокой чувствительностью маржи к снижению ставки (ВТБ) — эффект восстановления NIM",
   "банки с сильным капиталом, способные наращивать портфель в фазу восстановления (Сбер)",
   "в высокоставочном режиме — банки с дешёвым розничным фондированием (много текущих счетов)"
  ],
  "who_suffers": [
   "капиталодефицитные банки, вынужденные к допэмиссиям и урезанию дивидендов (ВТБ)",
   "банки с тонкой маржой в фазе высокой ставки (ВТБ на пике 2025)",
   "банки со слабым качеством активов при затяжной жёсткой ДКП (рост резервов)"
  ],
  "company_position": "ВТБ выигрывает на смягчении ДКП сильнее сектора по марже, но проигрывает по капиталу и дивидендной устойчивости; чистый эффект зависит от скорости снижения ставки против скорости вызревания просрочки.",
  "certainty": "judgement"
 },
 "cycle_position": {
  "phase": "замедление / начало смягчения ДКП",
  "where_company": "ВТБ проходит нижнюю точку по NIM (2025) и восстанавливается (1кв2026 NIM 3,3%); высокий маржинальный рычаг на развороте ставки, но тонкий капитал ограничивает участие в восстановлении кредита",
  "cyclical_or_defensive": "циклическая (высокая чувствительность к ставке и кредитному циклу)",
  "certainty": "judgement"
 },
 "rate_trajectory": {
  "base": {
   "text": "Плавное снижение ставки к ~12% (средняя-2026) с трога FY2025 ~18%: NIM восстанавливается к ~2,5-3%, прибыль заметно превышает нормализованный 2025.",
   "macro": "ставка ~12%, курс ~83, инфляция к ~5%, ВВП ~1,8%, зарплаты ~11%",
   "financials_delta": "ЧП операционная (норм.) ~509 млрд (от 364 в 2025): NIM +≈150, рост CoR −≈11, объём +≈2, зарплаты +≈4. Отчётная ~600-620 (+~90-110 разовых) — в русле гайденса менеджмента 600-650",
   "triggers": [
    "устойчивое замедление инфляции к 4-5%",
    "снижение инфляционных ожиданий",
    "охлаждение кредита без всплеска дефолтов"
   ]
  },
  "hawkish": {
   "text": "Ставка застревает на 14-15% из-за бюджетного дефицита и инфляционных ожиданий: NIM восстанавливается медленно, CoR растёт, капитал под давлением, дивиденды урезаны.",
   "macro": "ставка ~15%, курс ~90, инфляция не тормозит, ВВП ~0,8%, зарплаты ~14%",
   "financials_delta": "ЧП операционная (норм.) ~366 млрд (≈уровень 2025): слабое восстановление NIM +≈75 гасится ростом CoR −≈66 и зарплат. Отчётная ~450-490",
   "triggers": [
    "бюджетный дефицит выше плана (структурный до 2029)",
    "разгон зарплат",
    "core-инфляция не тормозит",
    "рубль слабеет"
   ]
  },
  "dovish": {
   "text": "Агрессивное снижение к ~10%: NIM восстанавливается к историческим уровням, розничный спрос оживает, зарплатная инфляция тормозит, прибыль к рекорду.",
   "macro": "ставка ~10%, курс ~80, инфляция к цели, ВВП ~2,5%, зарплаты ~9%",
   "financials_delta": "ЧП операционная (норм.) ~586 млрд: NIM +≈200, CoR снижается +≈7, объём +≈7, дезинфляция зарплат +≈8. Отчётная ~650-700",
   "triggers": [
    "устойчивое замедление инфляции и спроса",
    "охлаждение кредита",
    "снижение геополитической напряжённости на рынке ОФЗ"
   ]
  },
  "implication_for_company": "ВТБ чувствительнее всего к скорости снижения ставки — среди крупных банков максимальный рычаг маржи на смягчении. Главный риск — ястребиный сценарий: тонкий капитал не выдержит долгой высокой ставки без новых допэмиссий.",
  "certainty": "judgement"
 },
 "valuation_bridge": {
  "text": "Для банка DCF неприменим; ставка двигает капитализацию ВТБ через два канала: (1) стоимость капитала Ke и (2) устойчивый ROE через NIM. Снижение ставки одновременно снижает Ke (растёт справедливый P/BV по Гордону) и повышает ROE (шире маржа) — двойной положительный рычаг для оценки.",
  "direction": "давление вверх при снижении ставки",
  "dcf_channels": {
   "discount_rate": "ставка ↓ → Rf (длинная ОФЗ) и Ke ↓ → справедливый P/BV = (ROE−g)/(Ke−g) растёт нелинейно (знаменатель мал при Ke ~26%)",
   "terminal_growth": "g стабилен ~3,5%; сжатие спреда (Ke−g) при снижении ставки — основной рычаг переоценки от книги",
   "fcf": "у банка вместо FCF — ROE; снижение ставки → NIM ↑ → ROE ↑ (та же чувствительность, что в sensitivities — не считать дважды)"
  },
  "rate_sensitivity_capitalization": {
   "estimate": "−100 б.п. ставки ≈ +8…15% к обоснованной капитализации (через Ke и ROE совместно; для ВТБ выше сектора из-за маржинального рычага)",
   "assumption": "перенос ставки в Rf/Ke, устойчивый ROE растёт с восстановлением NIM; оценка чувствительна к тому, доходит ли капитал до акционера (размывание)",
   "certainty": "estimate"
  },
  "duration_note": "ВТБ чувствителен и к ставке дисконтирования (через Ke), и к текущей марже (через ROE) — двойная чувствительность; но реализация апсайда ограничена размыванием капитала.",
  "reconcile_with_finance": "Блок «Финансы» использует Ke 26,3% (Rf 14,6% + β 1,3 × ERP 9,0%) и устойчивый ROE 13,3% в P/BV×ROE. Наша rate-чувствительность объясняет их модель каналами Ke и ROE; абсолютную цену (коридор 48-151 ₽) считают они. ВАЖНО про расхождение: наш «нейтральный» ориентир прибыли ~490 млрд (ROE ~18% при ставке 11%) ВЫШЕ устойчивого ROE Финансов 13,3% — это не противоречие, а разные понятия: 13,3% — through-cycle медиана 2018-2025 (включает трог 2025 и эффект размывания капитала), а «нейтраль» — точечная операционная прибыль при благоприятной ставке до разовых. Для оценки корректно берётся консервативный through-cycle 13,3%.",
  "certainty": "judgement"
 },
 "endogeneity": {
  "text": "Ставка держится высокой не только из-за инфляции: структурный бюджетный дефицит до 2029 и повышенные инфляционные ожидания заставляют ЦБ держать жёсткость дольше «чистой» макрологики. ЦБ прямо сигналит, что пространство для снижения сузилось и прогноз средней ставки может быть пересмотрен вверх.",
  "sustainability_note": "Для ВТБ это ключевой риск: чем дольше высокая ставка держится по фискальным причинам, тем дольше зажата NIM и тоньше капитал — восстановление прибыли может оказаться медленнее гайденса менеджмента.",
  "certainty": "judgement"
 },
 "bottom_line": {
  "text": "Макросреда для ВТБ смешанная с уклоном в осторожный позитив: банк проходит дно по марже, и снижение ставки — его главный рычаг восстановления прибыли (сильнее сектора). Но высокий уровень ставки пока давит на NIM, растёт стоимость риска и зарплатные издержки, а тонкий капитал (Н20.0 9,8%) превращает часть прибыли в топливо для восстановления норматива, а не в дивиденды. Главный риск — ястребиный сценарий: застрявшая по фискальным причинам высокая ставка бьёт по ВТБ сильнее, чем по капитализированным конкурентам.",
  "effect": "mixed",
  "main_risk": "маржа",
  "certainty": "judgement"
 },
 "signal_macro_regime": {
  "rate_vector": "down",
  "inflation_vector": "down",
  "fx_vector": "ruble_weakening",
  "cycle_phase": "замедление",
  "horizon": "2-4 квартала",
  "scenario_financials_for_finance": "ЧП НОРМАЛИЗОВАННАЯ (операционная, для оценки): база ~509 млрд, ястреб ~366, голубь ~586. ОТЧЁТНАЯ (гайденс менеджмента, +~90-110 разовых): база ~600-620, ястреб ~450-490, голубь ~650-700. Нормализованный базовый 2025 = 364. Драйвер — восстановление NIM от трога 0,52%; сдерживают рост CoR, зарплаты и размывание капитала (прибыль не вся доходит до акционера). Отдаём в «Финансы» как вход, не пересчитывать оценку у нас."
 },
 "sources": [
  {
   "id": "src_f1",
   "type": "official",
   "title": "ВТБ — financials.json (МСФО 2025, инфографика финотчётности)",
   "period": "2016-2025",
   "url": "https://www.vtb.ru/ir/statements/results/",
   "reliability": "medium"
  },
  {
   "id": "src_1",
   "type": "regulator",
   "title": "Банк России — решение по ключевой ставке 19.06.2026 (14,25%), инфляция 5,6%",
   "period": "2026-06",
   "url": "https://www.cbr.ru/press/pr/?file=19062026_133000key.htm",
   "reliability": "high"
  },
  {
   "id": "src_2",
   "type": "media",
   "title": "Forbes — ослабление рубля в июне 2026 (~78,7), отмена аукциона ОФЗ, RGBI к минимумам",
   "period": "2026-06",
   "url": "https://www.forbes.ru/investicii/564130-podustal-kak-i-pocemu-rubl-oslab-v-iune",
   "reliability": "medium"
  },
  {
   "id": "src_3",
   "type": "media",
   "title": "Interfax/Frankmedia — прогноз ВТБ на 2026: прибыль 600-650 млрд, NIM ~3%, CoR ~1,1%, Н20.0 ≥10,5%; отчёт 1кв2026 NIM 3,3%",
   "period": "2026",
   "url": "https://www.interfax.ru/business/1074550",
   "reliability": "medium"
  }
 ],
 "data_flags": [
  "ТЕМПОРАЛЬНАЯ СВЯЗКА (устранён разрыв): macro_current.key_rate=18% = СРЕДНЯЯ ставка FY2025 (не спот 14,25% на июль-2026), чтобы период макро совпадал с якорной прибылью FY2025 и водопад/сценарии считались от одной базы. Спот 14,25% и NIM 3,3% (1кв2026) — в snapshot; сценарии измеряют путь от средней-2025 (~18%) к средней-2026 (база ~12%), поэтому база нормализованной прибыли ~509 млрд сходится с гайденсом менеджмента (отчётн. 600-650, +~90-110 разовых).",
  "NIM-чувствительность −25 млрд ЧП/−100 б.п. — БЛЕНДОВАЯ (эффективная) величина, откалибрована под гайденс менеджмента; у трога NIM-сенса круче (~0,3-0,4 пп/100 б.п.), у нейтрали площе — линейный коэффициент усредняет ~0,10-0,15 пп/100 б.п. Точная раскрытая менеджментом чувствительность отсутствует.",
  "CoR: through-cycle нейтраль принята 115 б.п. (медиана ВТБ ~1,15-1,2%, качество активов слабее сектора); FY2025 факт 0,99% — НИЖЕ нормы (умеренные резервы), в водопаде даёт небольшой ПЛЮС (~+29 млрд); forward-риск — рост розничной просрочки к 6-7% толкает CoR к 1,1-1,35%.",
  "LABOR-канал добавлен: ФОТ ≈45% opex 560,3 млрд, opex +17% г/г, CIR 57%. ±5 пп opex ≈ ±28 млрд до налога; коэффициент −1,9 млрд ЧП/+1 пп зарплат. Дезинфляция зарплат — часть голубиного апсайда.",
  "ОСТАТОК ВОДОПАДА +30 млрд (6% нейтрали) не подгоняется: отражает нелинейность восстановления NIM (линейный коэффициент не ловит крутизну отскока маржи у трога).",
  "НЕЙТРАЛЬ прибыли снижена 560→490 (ROE ~18% при ставке 11%). Остаётся выше устойчивого ROE Финансов 13,3% — это разные понятия (точечная нейтраль vs through-cycle медиана с учётом размывания); см. reconcile_with_finance.",
  "СВЕРКА С business_model.md: financials.json даёт ЧПД FY2025 = 190,4 млрд (NIM 0,52%, трог), но business_model.md указывает ЧПД ~433,6 млрд — расхождение требует сверки первоисточника (возможно, разные периметры/год/до или после резервов). В квант-слое использован якорь financials.json 190,4 млрд.",
  "«Выручка» для банка = операционный доход до резервов/расходов (985,4 млрд); «EBITDA» = доресервная операционная прибыль (425,1 млрд) — банковские аналоги, не классические метрики.",
  "Разовое +120 млрд (ОНА + роспуск резервов 2025) — оценка (judgement) из моста нормализации в financials.json; точная сумма не раскрыта.",
  "ЗАПРОС financial-analyst (при необходимости уточнения): раскрытая менеджментом чувствительность NIM к ставке, дюрация и FVTPL/FVOCI-разбивка портфеля ценных бумаг, доля активов/пассивов по плавающей ставке; сверка ЧПД FY2025 (190,4 vs 433,6 в business_model) — восполнить в financials.json для точной квантификации rate-канала."
 ]
}